echopy/__init__.py
echopy/analysis/__init__.py
echopy/analysis/fda.py
echopy/plotting/__init__.py
echopy/plotting/cmaps.py
echopy/preprocessing/__init__.py
echopy/preprocessing/report.py
echopy/processing/__init__.py
echopy/processing/correct_absorption.py
echopy/processing/correct_es60triangle.py
echopy/processing/correct_soundspeed.py
echopy/processing/get_background.py
echopy/processing/mask_attenuated.py
echopy/processing/mask_impulse.py
echopy/processing/mask_multifrequency.py
echopy/processing/mask_range.py
echopy/processing/mask_seabed.py
echopy/processing/mask_shoals.py
echopy/processing/mask_signal2noise.py
echopy/processing/mask_stationary.py
echopy/processing/mask_transient.py
echopy/processing/resample.py
echopy/reading/__init__.py
echopy/reading/read_calibration.py
echopy/utils/__init__.py
echopy/utils/transform.py
echopy/writing/__init__.py
echopy-1.1.0.dist-info/LICENSE.md
echopy-1.1.0.dist-info/METADATA
echopy-1.1.0.dist-info/WHEEL
echopy-1.1.0.dist-info/top_level.txt
echopy-1.1.0.dist-info/RECORD
