Metadata-Version: 2.1
Name: echopy
Version: 1.1.0
Summary: Fisheries acoustic data processing in Python
Home-page: https://github.com/open-ocean-sounding/echopy
Author: EchoPY
Author-email: echopy@protonmail.com
License: UNKNOWN
Platform: UNKNOWN
Classifier: Programming Language :: Python :: 3
Classifier: License :: OSI Approved :: MIT License
Classifier: Operating System :: OS Independent
